setup.py
Gaussian_Binomial_distro/Binomialdistribution.py
Gaussian_Binomial_distro/Gaussiandistribution.py
Gaussian_Binomial_distro/Generaldistribution.py
Gaussian_Binomial_distro/__init__.py
Gaussian_Binomial_distro.egg-info/PKG-INFO
Gaussian_Binomial_distro.egg-info/SOURCES.txt
Gaussian_Binomial_distro.egg-info/dependency_links.txt
Gaussian_Binomial_distro.egg-info/not-zip-safe
Gaussian_Binomial_distro.egg-info/top_level.txt