Metadata-Version: 1.0
Name: Gaussian-Binomial-distro
Version: 0.1
Summary: Gaussian and Binomal distributions
Home-page: UNKNOWN
Author: Edper Castro
Author-email: UNKNOWN
License: UNKNOWN
Platform: UNKNOWN
